{
  "_help": "Salin ke remotes.json lalu isi. Semua konfigurasi SSH/VNC ada DI SINI (tak perlu .env, kecuali sakelar REMOTE_ENABLE=1). KEY device = IP di MONITORING (pin.ip). ssh.host = IP SSH sebenarnya. Auth SSH (urutan prioritas): keyFile (path) > password (langsung) > passwordEnv (nama env). Taruh yang UMUM di 'defaults' (port/username/password) → tiap device baru cukup host+label+group. remotes.json TIDAK di-commit (gitignore) — sama amannya dengan .env, tapi satu tempat. RBAC (opsional): isi 'roles' + 'group', lalu set role user: node twinscape/adduser.js <user> <pass> --role <role>. vnc.startCommand (opsional): jalankan x11vnc via SSH sebelum konek, TANPA -bg.",
  "roles": {
    "admin":    { "remote": "*" },
    "operator": { "remote": ["group:injection"] },
    "viewer":   { "remote": [] }
  },
  "defaults": {
    "ssh": { "port": 22, "username": "admin", "password": "GANTI-password-bersama" }
  },
  "devices": {
    "10.10.1.50": {
      "label": "Server Rak A — SSH + VNC",
      "group": "injection",
      "ssh": { "host": "192.168.9.50" },
      "vnc": { "host": "192.168.9.50", "port": 5900, "startCommand": "x11vnc -display :0 -rfbport 5900 -nopw -forever", "startDelayMs": 2000 }
    },
    "10.10.1.51": {
      "label": "Switch — user & password sendiri",
      "group": "network",
      "ssh": { "host": "192.168.9.51", "username": "ops", "password": "pass-switch" }
    },
    "10.10.1.52": {
      "label": "PC Ops — pakai SSH key (paling aman)",
      "group": "office",
      "ssh": { "host": "192.168.9.52", "keyFile": "/home/user/.ssh/twinscape_remote" }
    }
  }
}
