{
  "version": 1,
  "units": "m",
  "walls": [],
  "floors": [
    {
      "x": 0,
      "z": 0,
      "w": 2,
      "d": 20,
      "type": "custom",
      "color": "#ffffff",
      "order": 1
    },
    {
      "x": 0,
      "z": 0,
      "w": 30,
      "d": 2,
      "type": "custom",
      "color": "#ffffff",
      "order": 2
    },
    {
      "x": 0,
      "z": 0,
      "w": 1,
      "d": 20,
      "type": "green",
      "color": "#ffffff",
      "order": 3
    },
    {
      "x": 0,
      "z": 0,
      "w": 30,
      "d": 1,
      "type": "green",
      "color": "#ffffff",
      "order": 4
    },
    {
      "x": 0,
      "z": 0,
      "w": 30,
      "d": 20,
      "type": "concrete",
      "color": "#3a3f47",
      "order": -1
    }
  ],
  "models": [
    {
      "url": "/models/injection_machine.glb",
      "name": "injection_machine",
      "deviceIp": "",
      "position": [
        -7,
        0,
        7.5
      ],
      "rotation": [
        3.142,
        0,
        3.142
      ],
      "scale": [
        1.939,
        1,
        1
      ]
    },
    {
      "url": "/models/injection_machine.glb",
      "name": "injection_machine",
      "deviceIp": "",
      "position": [
        -7,
        0,
        5
      ],
      "rotation": [
        3.142,
        0,
        3.142
      ],
      "scale": [
        1.939,
        1,
        1
      ]
    },
    {
      "url": "/models/injection_machine.glb",
      "name": "injection_machine",
      "deviceIp": "",
      "position": [
        -7,
        0,
        2.5
      ],
      "rotation": [
        3.142,
        0,
        3.142
      ],
      "scale": [
        1.939,
        1,
        1
      ]
    },
    {
      "url": "/models/injection_machine.glb",
      "name": "injection_machine",
      "deviceIp": "",
      "position": [
        -7,
        0,
        -3.5
      ],
      "rotation": [
        3.142,
        0,
        3.142
      ],
      "scale": [
        1.939,
        1,
        1
      ]
    },
    {
      "url": "/models/injection_machine.glb",
      "name": "injection_machine",
      "deviceIp": "",
      "position": [
        -7,
        0,
        -6.5
      ],
      "rotation": [
        3.142,
        0,
        3.142
      ],
      "scale": [
        1.939,
        1,
        1
      ]
    },
    {
      "url": "/models/injection_machine.glb",
      "name": "injection_machine",
      "deviceIp": "",
      "position": [
        4.5,
        0,
        -5.5
      ],
      "rotation": [
        0,
        1.571,
        0
      ],
      "scale": [
        1.497,
        1,
        1
      ]
    },
    {
      "url": "/models/injection_machine.glb",
      "name": "injection_machine",
      "deviceIp": "",
      "position": [
        7.5,
        0,
        -5.5
      ],
      "rotation": [
        0,
        1.571,
        0
      ],
      "scale": [
        1.497,
        1,
        1
      ]
    },
    {
      "url": "/models/injection_machine.glb",
      "name": "injection_machine",
      "deviceIp": "",
      "position": [
        10.5,
        0,
        -5.5
      ],
      "rotation": [
        0,
        1.571,
        0
      ],
      "scale": [
        1.497,
        1,
        1
      ]
    },
    {
      "url": "/models/glassroom_oasis.glb",
      "name": "glassroom_oasis",
      "deviceIp": "",
      "position": [
        3,
        0,
        2.5
      ],
      "rotation": [
        -1.571,
        0,
        0
      ],
      "scale": [
        0.599,
        0.639,
        1.018
      ]
    },
    {
      "url": "/models/panel_iot.glb",
      "name": "panel_iot",
      "deviceIp": "",
      "position": [
        -2.5,
        0.5,
        2.5
      ],
      "rotation": [
        -1.571,
        0,
        1.571
      ],
      "scale": [
        1,
        1,
        1
      ]
    },
    {
      "url": "/models/bumper_rack.glb",
      "name": "bumper_rack",
      "deviceIp": "",
      "position": [
        10,
        0,
        6
      ],
      "rotation": [
        -1.571,
        0,
        -1.571
      ],
      "scale": [
        0.688,
        1.071,
        0.838
      ]
    },
    {
      "url": "/models/bumper_rack.glb",
      "name": "bumper_rack",
      "deviceIp": "",
      "position": [
        3,
        0,
        6
      ],
      "rotation": [
        -1.571,
        0,
        -1.571
      ],
      "scale": [
        0.688,
        1.071,
        0.838
      ]
    },
    {
      "url": "/models/bumper_rack.glb",
      "name": "bumper_rack",
      "deviceIp": "",
      "position": [
        4,
        0,
        6
      ],
      "rotation": [
        -1.571,
        0,
        -1.571
      ],
      "scale": [
        0.688,
        1.071,
        0.838
      ]
    },
    {
      "url": "/models/bumper_rack.glb",
      "name": "bumper_rack",
      "deviceIp": "",
      "position": [
        5,
        0,
        6
      ],
      "rotation": [
        -1.571,
        0,
        -1.571
      ],
      "scale": [
        0.688,
        1.071,
        0.838
      ]
    },
    {
      "url": "/models/bumper_rack.glb",
      "name": "bumper_rack",
      "deviceIp": "",
      "position": [
        6,
        0,
        6
      ],
      "rotation": [
        -1.571,
        0,
        -1.571
      ],
      "scale": [
        0.688,
        1.071,
        0.838
      ]
    },
    {
      "url": "/models/bumper_rack.glb",
      "name": "bumper_rack",
      "deviceIp": "",
      "position": [
        7,
        0,
        6
      ],
      "rotation": [
        -1.571,
        0,
        -1.571
      ],
      "scale": [
        0.688,
        1.071,
        0.838
      ]
    },
    {
      "url": "/models/bumper_rack.glb",
      "name": "bumper_rack",
      "deviceIp": "",
      "position": [
        8,
        0,
        6
      ],
      "rotation": [
        -1.571,
        0,
        -1.571
      ],
      "scale": [
        0.688,
        1.071,
        0.838
      ]
    },
    {
      "url": "/models/bumper_rack.glb",
      "name": "bumper_rack",
      "deviceIp": "",
      "position": [
        2,
        0,
        8
      ],
      "rotation": [
        -1.571,
        0,
        -1.571
      ],
      "scale": [
        0.688,
        1.071,
        0.838
      ]
    },
    {
      "url": "/models/bumper_rack.glb",
      "name": "bumper_rack",
      "deviceIp": "",
      "position": [
        3,
        0,
        8
      ],
      "rotation": [
        -1.571,
        0,
        -1.571
      ],
      "scale": [
        0.688,
        1.071,
        0.838
      ]
    },
    {
      "url": "/models/bumper_rack.glb",
      "name": "bumper_rack",
      "deviceIp": "",
      "position": [
        8,
        0,
        8
      ],
      "rotation": [
        -1.571,
        0,
        -1.571
      ],
      "scale": [
        0.688,
        1.071,
        0.838
      ]
    },
    {
      "url": "/models/bumper_rack.glb",
      "name": "bumper_rack",
      "deviceIp": "",
      "position": [
        7,
        0,
        8
      ],
      "rotation": [
        -1.571,
        0,
        -1.571
      ],
      "scale": [
        0.688,
        1.071,
        0.838
      ]
    },
    {
      "url": "/models/bumper_rack.glb",
      "name": "bumper_rack",
      "deviceIp": "",
      "position": [
        6,
        0,
        8
      ],
      "rotation": [
        -1.571,
        0,
        -1.571
      ],
      "scale": [
        0.688,
        1.071,
        0.838
      ]
    },
    {
      "url": "/models/bumper_rack.glb",
      "name": "bumper_rack",
      "deviceIp": "",
      "position": [
        2,
        0,
        -2.5
      ],
      "rotation": [
        -1.571,
        0,
        -1.571
      ],
      "scale": [
        0.688,
        1.071,
        0.838
      ]
    },
    {
      "url": "/models/bumper_rack.glb",
      "name": "bumper_rack",
      "deviceIp": "",
      "position": [
        4,
        0,
        8
      ],
      "rotation": [
        -1.571,
        0,
        -1.571
      ],
      "scale": [
        0.688,
        1.071,
        0.838
      ]
    },
    {
      "url": "/models/bumper_rack.glb",
      "name": "bumper_rack",
      "deviceIp": "",
      "position": [
        9,
        0,
        8
      ],
      "rotation": [
        -1.571,
        0,
        -1.571
      ],
      "scale": [
        0.688,
        1.071,
        0.838
      ]
    },
    {
      "url": "/models/bumper_rack.glb",
      "name": "bumper_rack",
      "deviceIp": "",
      "position": [
        9,
        0,
        6
      ],
      "rotation": [
        -1.571,
        0,
        -1.571
      ],
      "scale": [
        0.688,
        1.071,
        0.838
      ]
    },
    {
      "url": "/models/bumper_rack.glb",
      "name": "bumper_rack",
      "deviceIp": "",
      "position": [
        10,
        0,
        8
      ],
      "rotation": [
        -1.571,
        0,
        -1.571
      ],
      "scale": [
        0.688,
        1.071,
        0.838
      ]
    },
    {
      "url": "/models/bumper_rack.glb",
      "name": "bumper_rack",
      "deviceIp": "",
      "position": [
        11,
        0,
        6
      ],
      "rotation": [
        -1.571,
        0,
        -1.571
      ],
      "scale": [
        0.688,
        1.071,
        0.838
      ]
    },
    {
      "url": "/models/bumper_rack.glb",
      "name": "bumper_rack",
      "deviceIp": "",
      "position": [
        11,
        0,
        8
      ],
      "rotation": [
        -1.571,
        0,
        -1.571
      ],
      "scale": [
        0.688,
        1.071,
        0.838
      ]
    },
    {
      "url": "/models/bumper_rack.glb",
      "name": "bumper_rack",
      "deviceIp": "",
      "position": [
        3,
        0,
        -2.5
      ],
      "rotation": [
        -1.571,
        0,
        -1.571
      ],
      "scale": [
        0.688,
        1.071,
        0.838
      ]
    },
    {
      "url": "/models/bumper_rack.glb",
      "name": "bumper_rack",
      "deviceIp": "",
      "position": [
        12,
        0,
        6
      ],
      "rotation": [
        -1.571,
        0,
        -1.571
      ],
      "scale": [
        0.688,
        1.071,
        0.838
      ]
    },
    {
      "url": "/models/bumper_rack.glb",
      "name": "bumper_rack",
      "deviceIp": "",
      "position": [
        12,
        0,
        8
      ],
      "rotation": [
        -1.571,
        0,
        -1.571
      ],
      "scale": [
        0.688,
        1.071,
        0.838
      ]
    },
    {
      "url": "/models/bumper_rack.glb",
      "name": "bumper_rack",
      "deviceIp": "",
      "position": [
        -1.5,
        0,
        6.5
      ],
      "rotation": [
        -1.571,
        0,
        -1.571
      ],
      "scale": [
        0.688,
        1.071,
        0.838
      ]
    },
    {
      "url": "/models/bumper_rack.glb",
      "name": "bumper_rack",
      "deviceIp": "",
      "position": [
        -3.5,
        0,
        9
      ],
      "rotation": [
        -1.571,
        0,
        -3.142
      ],
      "scale": [
        0.688,
        1.071,
        0.838
      ]
    },
    {
      "url": "/models/bumper_rack.glb",
      "name": "bumper_rack",
      "deviceIp": "",
      "position": [
        5,
        0,
        8
      ],
      "rotation": [
        -1.571,
        0,
        -1.571
      ],
      "scale": [
        0.688,
        1.071,
        0.838
      ]
    },
    {
      "url": "/models/bumper_rack.glb",
      "name": "bumper_rack",
      "deviceIp": "",
      "position": [
        3,
        0,
        -4.5
      ],
      "rotation": [
        -1.571,
        0,
        -1.571
      ],
      "scale": [
        0.688,
        1.071,
        0.838
      ]
    },
    {
      "url": "/models/bumper_rack.glb",
      "name": "bumper_rack",
      "deviceIp": "",
      "position": [
        3,
        0,
        -6.5
      ],
      "rotation": [
        -1.571,
        0,
        -1.571
      ],
      "scale": [
        0.688,
        1.071,
        0.838
      ]
    },
    {
      "url": "/models/bumper_rack.glb",
      "name": "bumper_rack",
      "deviceIp": "",
      "position": [
        -3.5,
        0,
        -2
      ],
      "rotation": [
        -1.571,
        0,
        0
      ],
      "scale": [
        0.688,
        1.071,
        0.838
      ]
    },
    {
      "url": "/models/bumper_rack.glb",
      "name": "bumper_rack",
      "deviceIp": "",
      "position": [
        -6,
        0,
        -2
      ],
      "rotation": [
        -1.571,
        0,
        0
      ],
      "scale": [
        0.688,
        1.071,
        0.838
      ]
    },
    {
      "url": "/models/bumper_rack.glb",
      "name": "bumper_rack",
      "deviceIp": "",
      "position": [
        -8.5,
        0,
        -2
      ],
      "rotation": [
        -1.571,
        0,
        0
      ],
      "scale": [
        0.688,
        1.071,
        0.838
      ]
    }
  ],
  "pins": [
    {
      "x": -1.5,
      "z": 2.5,
      "ip": "172.19.88.17",
      "label": "IoT Node 001"
    },
    {
      "x": -4.5,
      "z": 1,
      "ip": "172.19.88.21",
      "label": "Printer M#5"
    }
  ],
  "texts": [
    {
      "x": 3,
      "y": 1.6,
      "z": 2.5,
      "text": "Oasis",
      "size": 1,
      "color": "#e2e8f0"
    },
    {
      "x": 0,
      "y": 4,
      "z": 0.5,
      "text": "Factory 2",
      "size": 1,
      "color": "#e2e8f0"
    }
  ],
  "lighting": {
    "exposure": 0.8,
    "sunElevation": 33,
    "sunAzimuth": 84,
    "sunIntensity": 1.8,
    "ambient": 0.35,
    "bloom": {
      "strength": 0,
      "threshold": 0.9,
      "radius": 0.5
    }
  },
  "camera": {
    "position": [
      24.726,
      19.358,
      26.938
    ],
    "target": [
      -3.463,
      -3.234,
      0.135
    ]
  }
}